__init__.py
error.py
latch.py
latchapp.py
latchauth.py
latchresponse.py
latchuser.py
test_sdk_latch_web3.py
latch_sdk_telefonica-2.0.2.dist-info/LICENSE.txt
latch_sdk_telefonica-2.0.2.dist-info/METADATA
latch_sdk_telefonica-2.0.2.dist-info/WHEEL
latch_sdk_telefonica-2.0.2.dist-info/top_level.txt
latch_sdk_telefonica-2.0.2.dist-info/RECORD
