Metadata-Version: 2.1
Name: latch-sdk-telefonica
Version: 2.0.2
Summary: latch sdk-pyhton
Author-email: Telefonica Latch <soporte.latch@telefonica.com>
Project-URL: Homepage, https://github.com/Telefonica/latch-sdk-python
Project-URL: Bug Tracker, https://github.com/Telefonica/latch-sdk-python
Classifier: Programming Language :: Python :: 3
Classifier: License :: OSI Approved :: GNU General Public License (GPL)
Classifier: Operating System :: OS Independent
Requires-Python: >=3.7
License-File: LICENSE.txt
Requires-Dist: Deprecated (==1.2.13)
Requires-Dist: python-dotenv (==0.21.0)
